Workbook
Name FBA仓: 新版仓库编码!$C$2:$C$498
Name FBA卫星仓: 新版仓库编码!$C$499:$C$508
Name 海外仓: 新版仓库编码!$C$571:$C$627
Name 空: 新版仓库编码!$D$630
Name 嘀仓海外仓: 新版仓库编码!$C$545:$C$570
Name 私人地址: 新版仓库编码!$C$628:$C$629
Name WAL仓: 新版仓库编码!$C$509:$C$544
Name 空列表: 新版仓库编码!$D$630

Sheet 新版客户货物运输委托书
A1: *序号 | B1: *FBA箱号 （连号用“-”表示） | C1: *中文品名 | D1: *英文品名 | E1: SKU码 | F1: *海关编码 | G1: *中文材质 | H1: *英文材质 | I1: *品牌 | J1: *品牌类型 | K1: 型号 | L1: *用途 | M1: *带电、磁 | N1: *总箱数 | O1: 单箱 净重 | P1: 单箱 毛重 | Q1: *单箱个数 | R1: *产品总个数 | S1: *申报单价 | T1: *申报总价 | U1: *申报币种 | V1: 采购单价 | W1: 采购总价 | X1: 采购币种 （默认人民币） | Y1: *长 cm | Z1: *宽 cm | AA1: *高 cm | AB1: ※图片（必填，需为浮动图片） | AC1: ※产品在平台链接 （必填） | AD1: 参考编号 | AE1: PO NO | AF1: *预计到仓时间 | AG1: *地址类型 | AH1: *仓库编码 | AI1: *收件国家 | AJ1: *收件地址 | AK1: *收件邮编 | AL1: 收件州/省 | AM1: *收件城市 | AN1: 收件公司 | AO1: *收件人 | AP1: *收件电话 | AQ1: 收件邮箱 | AR1: *指定路线 | AS1: *报关方式 | AT1: *清关方式 | AU1: 是否递延 | AV1: 收件税号 | AW1: 备注
A2: 1 | R2: =Q2*N2 -> 0 | T2: =R2*S2 -> 0 | X2: CNY | AC2: / | AF2: 46121.783 | AG2: FBA仓 | AH2: PHX3 | AI2: =IF(AH2="","",VLOOKUP(AH2,新版仓库编码!C:L,10,0)) -> US | AJ2: =IF(AH2="","",VLOOKUP(AH2,新版仓库编码!C:H,3,0)) -> 6835 West Buckeye Road | AK2: =IF(AH2="","",VLOOKUP(AH2,新版仓库编码!C:H,6,0)) -> 85043 | AL2: =IF(AH2="","",VLOOKUP(AH2,新版仓库编码!C:L,4,0)) -> AZ | AM2: =IF(AH2="","",VLOOKUP(AH2,新版仓库编码!C:K,5,0)) -> Phoenix | AN2: =IF(AH2="","",VLOOKUP(AH2,新版仓库编码!C:L,8,0)) -> Amazon Fulfillment Center PHX3 | AO2: =IF(AH2="","",VLOOKUP(AH2,新版仓库编码!C:K,7,0)) -> Amazon PHX3 | AP2: =IF(AH2="","",VLOOKUP(AH2,新版仓库编码!C:K,9,0)) -> 0000000000
R3: =Q3*N3 -> 0 | T3: =R3*S3 -> 0 | AI3: =IF(AH3="","",VLOOKUP(AH3,新版仓库编码!C:L,10,0)) | AJ3: =IF(AH3="","",VLOOKUP(AH3,新版仓库编码!C:H,3,0)) | AK3: =IF(AH3="","",VLOOKUP(AH3,新版仓库编码!C:H,6,0)) | AL3: =IF(AH3="","",VLOOKUP(AH3,新版仓库编码!C:L,4,0)) | AM3: =IF(AH3="","",VLOOKUP(AH3,新版仓库编码!C:K,5,0)) | AN3: =IF(AH3="","",VLOOKUP(AH3,新版仓库编码!C:L,8,0)) | AO3: =IF(AH3="","",VLOOKUP(AH3,新版仓库编码!C:K,7,0)) | AP3: =IF(AH3="","",VLOOKUP(AH3,新版仓库编码!C:K,9,0))
R4: =Q4*N4 -> 0 | T4: =R4*S4 -> 0

Sheet 栏位填写说明
A1: 货物下单信息填写规范表
A2: 表头字段 | B2: 填写规范要求 | C2: 正确示例 | D2: 错误示例 | E2: 关键备注 | F2: 是否为新增栏位
A3: *序号 | B3: 用于区分不同票数，同一订单请务必填写相同序号 | C3: 1 | D3: 同一订单下填了001、002两个不同序号 | E3: 同一订单序号保持一致 | F3: 是
A4: *FBA 箱号 （连号用 “-” 表示） | B4: 1. 编码规则：12 位 FBAID + U + 补 0（个位数补 5 个 0、十位数补 4 个 0、百位数补 3 个 0） + 箱数； 2. 多子单：用 “-” 连接起止箱号，确保连号无断档，中间不可有任何其他符号或空格。 3.到FBA仓库为必填其他地址可为空 | C4: 1箱：FBA123456789U000001或1-1 1-15箱：FBA123456789U000001-FBA123456789U000015或1-15 108-112箱：FBA123456789U000108-FBA123456789U000112或108-112 | D4: 1. FBA12345678U000001（FBAID 仅 11 位） 2. FBA123456789U00015（十位数少补 1 个 0） 3. FBA123456789U000011~FBA123456789U000015 （用 “~” 连接） 4.FBA123456789U000001-U000015（缺少前缀） | E4: 12 位 FBAID 需逐位复制，不可增减；箱数需与实际货物一致，多子单范围需连续 | F4: 否
A5: *中文品名 | B5: 1. 用规范中文，完整体现 “材质 + 功能 + 品类 + 关键属性”（如款式、容量）； 2. 禁用 “配件”“样品”“礼品”“杂货” 等模糊表述。 | C5: 1. 100% 纯棉女士中长款连帽卫衣 2. ABS 塑料儿童益智拼装积木（300 颗粒） 3. 不锈钢家用多功能高压锅（5L） | D5: 1. 服装（未明确材质、款式） 2. 玩具（未明确类型、材质） 3. 厨房配件（模糊表述） | E5: 需与商品实物、平台链接描述一致，避免因属性不全触发海关查验 | F5: 否
A6: *英文品名 | B6: 1. 国际通用名称，与中文品名完全对应； 2. 首字母大写（介词 / 连词除外），无拼写错误。 | C6: 1. 100% Cotton Women's Mid-Length Hoodie 2. ABS Plastic Kids' Educational Building Blocks (300pcs) 3. Stainless Steel Household Multi-Functional Pressure Cooker (5L) | D6: 1. Women's Clothes（与中文 “卫衣” 不对应） 2. abs plastic blocks（首字母未大写） 3. Stainless Steel Cooker（漏 “5L” 关键属性） | E6: 符合目的国语言习惯，确保中外品名一一匹配，避免简写导致歧义 | F6: 否
A7: SKU 码 | B7: 填写库存系统唯一编码，建议含 “品类 + 规格 + 款号”（便于区分和追踪）。 | C7: 1. TS-W-M001（TS=T 恤，W = 女士，M001 = 中长款） 2. BLOCK-K-300（BLOCK = 积木，K = 儿童，300 = 颗粒数） 3. POT-S-5L（POT = 锅具，S = 不锈钢，5L = 容量） | D7: 1. 001、通用码（无含义，无法区分） 2. TS-W-M001（重复用于男士 T 恤） | E7: 确保 SKU 唯一性，便于内部库存核对和物流追踪 | F7: 否
A8: *海关编码 （10 位 HS 编码） | B8: 1. 提供完整 10 位编码，不可缺位； 2. 匹配商品材质、用途、监管条件，不确定时联系服务商确认。 3.自税的订单按照目的国清关编码来填写；包税的订单不做限制 | C8: 1. 纯棉女士卫衣：6110200090 2. 儿童拼装积木：9503006000 3. 不锈钢高压锅：7323930000 | D8: 1. 6110（仅 4 位） 2. 950300（仅 6 位） 3. 7323（仅 4 位，无法定位商品） | E8: 参考海关编码查询网址https://www.likecha.com/tools/hscode.html 英国海关编码税率查询https://www.trade-tariff.service.gov.uk/find_commodity 欧洲海关编码税率查询https://ec.europa.eu/taxation_customs/dds2/taric/taric_consultation.jsp?Lang=en 美国海关编码税率查询https://hts.usitc.gov/ | F8: 否
A9: *材质（中文） | B9: 1. 单一材质注 “100% XX”，混合材质按占比从高到低标注； 2. 含竹 / 木 / 草等植物成分必须注明； 3. 禁用 “木质”“布料”“混合材质” 等模糊表述。 | C9: 1. 100% 聚酯纤维 2. 70% 棉 + 30% 氨纶 3. 松木（含植物成分）4. ABS 塑料 + 钢化玻璃（各 50%） | D9: 1. 布料（未明确材质） 2. 木质（未明确木材种类） 3. 混合材质（未拆分成分） 4. 塑料 + 玻璃（未标比例） | E9: 植物成分涉及检疫要求，漏填可能导致查验；混合材质比例需实际检测，不可估算 | F9: 否
A10: *材质（英文） | B10: 1. 与中文材质完全对应，比例格式统一； 2. 用国际通用术语，无缩写（特殊约定除外）。 | C10: 1. 100% Polyester 2. 70% Cotton + 30% Spandex 3. Pine Wood (Contains Plant Components) 4. 50% ABS Plastic + 50% Tempered Glass | D10: 1. 100% Fabric（与 “聚酯纤维” 不对应） 2. 70% Cot + 30% Spandex（缩写不规范） 3. Wood (Plant Component)（未明确木材种类） | E10: 避免直译错误（如 “氨纶” 译 “Spandex”，不译 “Elastane”） | F10: 否
A11: *品牌 | B11: 1. 无品牌：明确填 “无品牌”（产品、标签、外包装上都无品牌，不可填店铺名、产品名）； 2. 有品牌：填 “英文 + 中文”（产品或标签或外包含 ®/TM/LOGO 需如实申报）； 3. 备案品牌：需提供授权截图，授权人匹配报关单境内发货人。 | C11: 1. 备案品牌：华为 HUAWEI（附授权） 2. 非备案品牌：耐克 NIKE 3. 无品牌：无品牌 | D11: 1. XX 运动旗舰店（店铺名误作品牌） 2. 无线蓝牙耳机（产品名误作品牌） 3. 空白（无品牌时未填写） | E11: 品牌名称需与商品标签 / 包装一致，不可简写（如 “耐克” 不代 “NIKE 耐克”） ，海关备案品牌查询网址 http://202.127.48.145:8888/zscq/search/jsp/vBrandSearchIndex.jsp | F11: 否
A12: *品牌类型 | B12: 必选以下 5 类，不可自定义，需与 “品牌” 匹配： 无品牌：是指出货实物商品或包装上无任何标志或品牌名 境内自主品牌：境内企业自主开发并拥有知识产权的品牌，如华为 境内收购品牌：境内企业收购的原境外品牌如联想 IBM 境外品牌（贴牌）：境内企业代工贴牌生产中使用的境外品牌，如代工厂 ZARA 境外品牌（其他）：除贴牌生产外使用的境外品牌，如进口授权耐克 | C12: 1. 华为 HUAWEI→境内自主品牌 2. 联想 IBM→境内收购品牌 3. 代工厂 ZARA→境外品牌（贴牌） 4. 无品牌→无品牌 | D12: 1. 耐克 NIKE→境内自主品牌（归属错误） 2. 无品牌→境外品牌（其他）（逻辑错误） 3. 自定义 “进口品牌”（未选指定类别） | E12: 错误选择会影响海关品牌属性判定，可能导致通关延误或退单 | F12: 否
A13: 型号 | B13: 1. 有标注（Model/Type/PN 等）：如实填完整型号（含字母、数字、符号）； 2. 无型号：明确填 “无型号”，不可填 “通用”“常规”。 | C13: 1. Model: MateBook X Pro 2024 2. PN: A1234-56783. 无型号：无型号 | D13: 1. MateBook X Pro（省略 “2024” 完整标识） 2. A1234（省略 “-5678”） 3. 通用款（无型号时自定义） | E13: 型号需照抄商品标注，不可自行简化或编造 | F13: 否
A14: *用途 | B14: 填写核心使用场景（简洁中文，如 “家用”“商用”“户外”），需与商品属性匹配。 | C14: 1. 家用（日常饮水保温） 2. 商用（办公室文件存储） 3. 户外露营（临时居住） | D14: 1. 使用（表述模糊，无实际意义） 2. 装东西（仅说明功能，未标场景） 3. 家用（用于工业生产，场景不符） | E14: 避免场景与商品功能脱节，如 “儿童玩具” 不可填 “商用” | F14: 否
A15: *带电、磁 | B15: 1. 带电：选 “带电 ”； 2. 带磁：选 “带磁”； 3. 无电无磁无纺织品：选 “普货”。 | C15: 1. 带电（如无线耳机） 2. 带磁（如音箱） 3. 普货（如塑料制品） | D15: 1. 带电（实际带电+带磁） 2. 无（实际带磁商品） | E15: 带电 / 带磁商品需额外提供电池备案 / 磁检报告（如涉及） | F15: 否
... A33: *PO NO | B33: 1.填写亚马逊平台生成的8位PO号（从卖家后台“订单管理”复制，不可错填/漏填）； 2.非FBA可不填 | C33: 正确：12345678 | D33: 错误：123456（非8位标准格式）、自家订单号001 | E33: 需与平台订单一致，错误会导致无法预约，或送至错误地址 | F33: 否，仅调整填写顺序
A34: *预计到仓时间 | B34: 1.格式要求：日期 + 时间； 2.请根据货物实际情况，填写预计送达我司仓库时间（也可填写预计货好时间） | C34: 46242.763 | D34: 1.8/8 2.8月8 3.2026/8/8（无时间） | E34: 预计到仓时间影响排柜计划，请尽量准确填写， 如有变动请及时通知跟单客服。 | F34: 是
A35: *地址类型 | B35: 根据实际情况选择，不可自定义： FBA仓 FBA卫星仓 WAL仓 嘀仓海外仓 海外仓 私人地址 | C35: FBA仓 | D35: 1.送FBA仓地址类型选择私人地址 2.为空 | E35: 1.先选类型，再决定是否填仓库代码 2.地址类型错误会影响后续具体地址匹配、以及下单失败 | F35: 是
A36: *仓库编码 | B36: 1.FBA：填写亚马逊FBA仓库代码（如 ONT8、MAN1）。 2.大型海外仓：填写报价表上对应地址的仓库编码，如4PX-25261 3.无代码的商业/私人地址可不填 | C36: 1. 美国仓→ONT8、LAX92. 英国仓→MAN1、LHR33. 德国仓→MUC3、FRA1 | D36: 1. 美国加州仓（需用代码 “ONT8”） 2. ONT（代码缩写，缺 1 位） 3. MAN（代码缩写，缺 1 位） 4.私人地址填了仓库代码 | E36: 1.先视仓库类型决定是否需要填写 2.仓库代码错误会导致货物错发，需逐位核对平台仓单信息 | F36: 否，仅调整填写顺序
A37: *收件国家 | B37: 1.填写仓库编码公式自动匹配 2.无仓库编码，根据实际情况填写收件所在国家，建议用英文或标准国家代码 | C37: US | D37: 美国 | E37: 须与城市、邮编保持一致 | F37: 是
A38: *收件地址 | B38: 填写完整英文地址（含街道、城市、州 / 省、邮编、国家），如前面填写了仓库代码自行匹配 | C38: 1. ONT8：2430 E Central Ave, Ontario, CA 91761, USA 2. MAN1：1 Amazon Way, Manchester, M40 8AG, UK | D38: 1. Ontario, CA（地址不完整，缺街道、邮编） 2. 2430 E Central Ave, Los Angeles, CA 90001, USA（与 ONT8 代码不匹配）3. 亚马逊路 1 号，曼彻斯特（中文地址，需用英文） | E38: 需从平台仓单完整复制，避免拼写错误（如 “Ave” 误写为 “Av”） | F38: 否，仅调整填写顺序
A39: *收件邮编 | B39: 1.填写仓库编码公式自动匹配 2.无仓库编码，填写收件地址对应的准确邮政编码，须与城市、国家匹配 | C39: 90210 | D39: 自行编辑 | E39: 邮编错误会导致派送失败/或派送错误地址 | F39: 是
A40: 收件州/省 | B40: 1.填写仓库编码公式自动匹配 2.填写州、省或地区的全称或缩写 | C40: Berlin | D40: 不填 | E40: 填写错误会导致派送失败/或派送错误地址 | F40: 是
A41: *收件城市 | B41: 1.填写仓库编码公式自动匹配 2.无仓库编码，根据实际情况填写 | C41: Los Angeles | D41: Los Angele（缺少S） | E41: 须与邮编、国家一致 | F41: 是
A42: 收件公司 | B42: 填写公司法定注册全称，包含法律形式后缀（如 GmbH、AG、Sp. z o.o.），不写个人姓名 | C42: DDD GmbH、Procent Poland Sp. z o.o.、BMW AG | D42: DDD（缺后缀）、DDD公司（中文）、Herr Schmidt（人名） | E42: 部分地址缺少可能导致投递失败 | F42: 是
A43: *收件人 | B43: 1.填写仓库编码公式自动匹配 2.无仓库编码，填写实际签收人信息 | C43: DDD | D43: 张三 | E43: 正确填写 | F43: 是
A44: *收件电话 | B44: 1.填写仓库编码公式自动匹配 2.无仓库编码，填写收件人有效联系电话，含国际区号 | C44: +1 310 555 1212 | D44: 1234567（缺区号） | E44: 派送必备，务必准确 | F44: 是
A45: 收件邮箱 | B45: 使用国际通用格式，全部小写，@ 前后均不含空格或特殊字符（如中文符号）。域名应为有效注册域名，或使用国际标准测试域 | C45: 1.info@ddd.de 2.contact@example.com 3.sales@procent.pl | D45: 1.info@ddd,de（逗号） 2.INFO@DDD.DE（大写） 3.info@ddd公司.de（中文字符） 4.info@ddd（缺域名后缀） | E45: 邮箱错误可能到位无法提前预约等操作 | F45: 是
A46: *指定路线 | B46: 正确填写我司可出货线路，不可自定义编辑，删增字段 | C46: 美国海运-钻龙特运卡派(BS)-华南 | D46: 钻龙/普船 | E46: 指定线路如原计划下A渠道填写为B会影响价格，请慎重 | F46: 是
A47: *报关方式 | B47: 1.如需出口退税填写自备，反之填写买单 2.如部分报关选择填写为自备，在备注栏位填写实际需要报关箱号/品名 | C47: 根据实际情况填写 | D47: 未选，自备选择买单 | E47: 填写错误可能会导致漏报关/或时效延误 | F47: 是
A48: *清关方式 | B48: 根据路线自动匹配，例如渠道带有BS则为包税、带有ZS则为自税 | C48: 表格自动识别 | D48: 选错与实际线路不匹配，下单渠道BS手动改为ZS | E48: 根据所选线路自动匹配，不可自定义； 选择ZS需提前确认资料是否齐全，否则影响清关带来额外费用 | F48: 是
A49: 是否递延 | B49: 如识别清关方式，包税为空，反之则需自行判断是否递延 | C49: 是 / 否 | E49: 须提前确认，递延需资质 | F49: 是
A50: 收件税号 | B50: 1.自税时填写； 2.美国自税可填1 3.可填后补 4.填写时需要确保系统已维护税号信息 | C50: 1.英国: GB123456789 2.德国：DE123456789 3.法国：FR12345648911 | D50: 1.英国: 123456789（缺前缀标识）、留空（实际需要时） 2.德国：DE123456 VAT12345 （格式不规范） 3.法国：FR1234 5678911（空格） | E50: 需确保系统中已维护对应税号信息 | F50: 是
A51: 备注 | B51: 根据实际需求填写，例如：特殊派送要求、约仓时段、联系人分机等补充信息 | C51: 1.A跟B订单需要合并报关 2.该票部分报关，XX品名买单 3.海外仓特殊入仓要求 （需提前1天预约，9:00-17:00派送） 4.其他 | D51: 1.无 （有需求时不写清楚） 2.看上面 （无效信息） 3.填写与货物无关的内容 4.前面填写A地址备注送B地址（前后矛盾） | E51: 非必填但有特殊需求时必须在此说明； 涉及报关、贴标、合并等操作务必写清楚，避免漏操作 | F51: 是
A52: 补充注意事项与风险提醒 | B52: 资料时效：需在货物抵仓前（参考截单时间）提交完整报关资料（合同、发票、箱单等），逾期可能导致货物滞留仓库，无法按原计划出运，产生额外费用。 信息一致性：核心字段（品名、HS 编码、品牌、型号）需与商品标签、包装、平台链接完全一致，如 “中文品名纯棉卫衣” 不可对应 “HS 编码 6110300090（化纤卫衣编码）”。 认证要求：产品涉及UL、Bluetooth等认证的，需同步提供有效授权证书（含型号、有效期）。
A53: 申报不实风险 | B53: 通关延误：查验、删改单导致货物滞留； 额外费用：查验费、滞箱费等由责任方承担； 法律风险：违反《海关法》面临行政处罚，情节严重追究刑事责任； 信用受损：影响海关信用等级，降低后续通关便利。
A54: 温馨提示： | B54: 1.表格第一列为表头，请勿修改； 2.请完整填写所有标*栏位，否则系统无法识别并提交订单； 3.表格前2列已预设公式，如需新增行，可复制使用； 4.所有新增栏位除序号外，均为原系统需要额外填写字段，填写顺序：先选【仓库类型】，再决定是否需要填【仓库代码】
A55: 免责声明 本表格内所有填写建议、比例参考、数据指引及操作提示，均系我司基于行业经验整理，仅供客户参考之用，不构成任何法律、税务、海关申报或其他专业领域的正式意见或承诺。客户应结合自身实际情况，独立核实并自行决定最终申报内容，对申报行为的合法性、真实性及准确性承担全部责任。我司不对因使用本表格信息而引发的任何直接或间接损失、风险或法律后果承担责任。所有事项的最终认定，均以相关主管部门的实际审核结果为准。

Sheet 新版仓库编码
A1: 目的地编码 | B1: 仓库类型 | C1: 仓库编码 | D1: 目的地 | E1: 地址 | F1: 州省 | G1: 城市 | H1: 邮编 | I1: 收件人 | J1: 公司 | K1: 电话 | L1: 目的地编码
A2: US | B2: FBA仓 | C2: PHX3 | D2: 美国 | E2: 6835 West Buckeye Road | F2: AZ | G2: Phoenix | H2: 85043 | I2: Amazon PHX3 | J2: Amazon Fulfillment Center PHX3 | K2: 0000000000 | L2: US
A3: US | B3: FBA仓 | C3: PHX5 | D3: 美国 | E3: 16920 W Commerce Drive | F3: AZ | G3: Goodyear | H3: 85338 | I3: Amazon PHX5 | J3: Amazon Fulfillment Center PHX5 | K3: 0000000000 | L3: US
A4: US | B4: FBA仓 | C4: PHX6 | D4: 美国 | E4: 4750 West Mohave St | F4: AZ | G4: Phoenix | H4: 85043-8305 | I4: Amazon PHX6 | J4: Amazon Fulfillment Center PHX6 | K4: 0000000000 | L4: US
A5: US | B5: FBA仓 | C5: PHX7 | D5: 美国 | E5: 800 N 75th Ave | F5: AZ | G5: Phoenix | H5: 85043 | I5: Amazon PHX7 | J5: Amazon Fulfillment Center PHX7 | K5: 0000000000 | L5: US
A6: US | B6: FBA仓 | C6: ONT2 | D6: 美国 | E6: 1910 E central Ave | F6: CA | G6: San Bernardino | H6: 92408-0123 | I6: Amazon(ONT2) | J6: Amazon Fulfillment Center(ONT2) | K6: 0000000000 | L6: US
A7: US | B7: FBA仓 | C7: ONT6 | D7: 美国 | E7: 24208 San Michele Rd | F7: CA | G7: Moreno Valley | H7: 92551 | I7: Amazon(ONT6) | J7: Amazon Fulfillment Center(ONT6) | K7: 0000000000 | L7: US
A8: US | B8: FBA仓 | C8: ONT8 | D8: 美国 | E8: 24300 Nandina Ave | F8: CA | G8: Moreno Valley | H8: 92551 | I8: Amazon(ONT8) | J8: Amazon Fulfillment Center(ONT8) | K8: 0000000000 | L8: US
A9: US | B9: FBA仓 | C9: OAK4 | D9: 美国 | E9: 1555 N. Chrisman Rd | F9: CA | G9: Tracy | H9: 95304-9370 | I9: Amazon OAK4 | J9: Amazon Fulfillment Center OAK4 | K9: 0000000000 | L9: US
A10: US | B10: FBA仓 | C10: OAK3 | D10: 美国 | E10: 255 Park Center Drive | F10: CA | G10: Patterson | H10: 95363-8876 | I10: Amazon OAK3 | J10: Amazon Fulfillment Center OAK3 | K10: 0000000000 | L10: US
A11: US | B11: FBA仓 | C11: ONT9 | D11: 美国 | E11: 2125 W. San Bernandino Ave Redlands, CA 92374-5005 | F11: CA | G11: Redlands | H11: 92374 | I11: Amazon(ONT9) | J11: Amazon Fulfillment Center(ONT9) | K11: 0000000000 | L11: US
A12: US | B12: FBA仓 | C12: SNA4 | D12: 美国 | E12: Amazon.com Services, Inc 2496 W Walnut Ave | F12: CA | G12: Rialto | H12: 92376-3009 | I12: Amazon SNA4 | J12: Amazon Fulfillment Center SNA4 | K12: 0000000000 | L12: US
... A86: US | B86: FBA仓 | C86: DET1 | D86: 美国 | E86: 39000 Amrhein RD Livonia, MI 48150-1043 | F86: MI | G86: Livonia | H86: 48150 | I86: Amazon Fulfillment Center DET1 | J86: Amazon Fulfillment Center DET1 | K86: 0000000000 | L86: US
A87: DE | B87: FBA仓 | C87: FRA3 | D87: 德国 | E87: Amazonstr. 1 Bad Hersfeld | G87: Obere K¨¹hnbac | H87: 36251 | I87: Amazon (FRA3) | J87: Amazon Fulfillment Center FRA3 | K87: 0000000000 | L87: DE
A88: DE | B88: FBA仓 | C88: MUC3 | D88: 德国 | E88: Amazonstrasse 1 | G88: Graben | H88: 86836 | I88: Amazon (MUC3) | J88: Amazon Fulfillment Center MUC3 | K88: 0000000000 | L88: DE
A89: DE | B89: FBA仓 | C89: DUS2 | D89: 德国 | E89: Amazonstrasse 1 | G89: Rheinberg | H89: 47495 | I89: Amazon (DUS2) | J89: Amazon Fulfillment Center DUS2 | K89: 0000000000 | L89: DE
A90: DE | B90: FBA仓 | C90: BER3 | D90: 德国 | E90: Havellandstraße 5 | G90: Brieselang | H90: 14656 | I90: Amazon (BER3) | J90: Amazon Fulfillment Center BER3 | K90: 0000000000 | L90: DE
A91: DE | B91: FBA仓 | C91: CGN1 | D91: 德国 | E91: Amazonstrasse 1 | G91: Kobern-Gondorf | H91: 56330 | I91: Amazon (CGN1） | J91: Amazon Fulfillment Center CGN1 | K91: 0000000000 | L91: DE
A92: PL | B92: FBA仓 | C92: P-WRO2 | D92: 波兰 | E92: z o.o. ul. Logistyczna 6 Bielany | G92: Wroclawskie | H92: 55-040 | I92: Amazon (WRO2-PL) | J92: Amazon Fulfillment Poland WRO2 | K92: 0000000000 | L92: PL
A93: CZ | B93: FBA仓 | C93: PRG2 | D93: 捷克 | E93: K Amazonu 235 | G93: Dobroviz | H93: 25261 | I93: Amazon （PRG2） | J93: Amazon Fulfilment Center PRG2 | K93: 0000000000 | L93: CZ
A94: DE | B94: FBA仓 | C94: DE-WRO1 | D94: 德国 | E94: via: Slam Poland Sp. z o.o. Am Zeugamt 4 Oschatz, Saxony | F94: Oschatz | G94: Saxony | H94: 04758 | I94: Amazon （WRO1 DE） | J94: Amazon Fulfilment Center WRO1 | K94: 0000000000 | L94: DE
A95: DE | B95: FBA仓 | C95: KTW1 | D95: 德国 | E95: Am Zeugamt 6, Oschatz, Saxony 04758 | F95: Saxony | G95: Oschatz | H95: 04758 | I95: Amazon （KTW1） | J95: Amm GmbH Co KG Spedition | K95: 0000000000 | L95: DE
A96: DE | B96: FBA仓 | C96: DTM2 | D96: 德国 | E96: Kaltbandstrasse 4 | F96: North Rhine-Westphalia | G96: Dortmund | H96: 44145 | I96: Amazon （DTM2） | J96: Amazon Fulfillment Center DTM2 | K96: 0000000000 | L96: DE
A97: DE | B97: FBA仓 | C97: DTM1 | D97: 德国 | E97: Raiffeisenstrasse 7 | G97: Werne | H97: 59368 | I97: Amazon （DTM1） | J97: Amazon Logistik Werne GmbH | K97: 0000000000 | L97: DE
A98: PL | B98: FBA仓 | C98: PL-WRO1 | D98: 波兰 | E98: Poland sp.z o o., Ul. Czekoladowa 1 | G98: Bielany Wroclawskie | H98: 55040 | I98: Amazon (WRO1) | J98: amazon.com | K98: 0000000000 | L98: PL
A99: UK | B99: FBA仓 | C99: EDI4 | D99: 英国 | E99: Way Dunfermline | G99: Fife | H99: KY11 8ST | I99: Amazon(EDI4) | J99: Amazon Fulfillment Center(EDI4) | K99: 0000 000 0000 | L99: UK
A100: UK | B100: FBA仓 | C100: CWL1 | D100: 英国 | E100: FFORDD AMAZON SWANSEA | F100: Wales | G100: SWANSEA | H100: SA1 8QX | I100: Amazon(CWL1) | J100: Amazon Fulfillment Center(CWL1) | K100: 0000 000 0000 | L100: UK
A101: UK | B101: FBA仓 | C101: EUK5 | D101: 英国 | E101: Phase Two, Kingston Park Flaxley Road | G101: Peterborough | H101: PE2 9EN | I101: Amazon(EUK5) | J101: Amazon Fulfillment Center(EUK5) | K101: 0000 000 0000 | L101: UK
A102: UK | B102: FBA仓 | C102: LBA1 | D102: 英国 | E102: Unit 1, Balby Carr Bank, Balby | G102: Doncaster | H102: DN4 5JS | I102: Amazon(LBA1) | J102: Amazon Fulfillment Center(LBA1) | K102: 0000 000 0000 | L102: UK
A103: UK | B103: FBA仓 | C103: BHX1 | D103: 英国 | E103: Towers Business Park Power Station Road Rugeley | G103: Staffordshire | H103: WS15 1LX | I103: Amazon(BHX1) | J103: Amazon Fulfillment Center(BHX1) | K103: 0000 000 0000 | L103: UK
A104: UK | B104: FBA仓 | C104: LTN4 | D104: 英国 | E104: EU SARL, Unit DC1 Prologis Dunstable | G104: East England | H104: LU5 4FE | I104: Amazon(LTN4) | J104: Amazon Fulfillment Center(LTN4) | K104: 0000 000 0000 | L104: UK
A105: UK | B105: FBA仓 | C105: MAN1 | D105: 英国 | E105: 6 Sunbank Lane Airport City Altrincham | G105: Manchester | H105: M90 5AA | I105: Amazon(MAN1) | J105: Amazon Fulfillment Center(MAN1) | K105: 0000 000 0000 | L105: UK
A106: UK | B106: FBA仓 | C106: LBA2 | D106: 英国 | E106: Unit 1 Iport Avenue Doncaster | G106: Yorkshire and the Humber | H106: DN11 0BG | I106: Amazon(LBA2) | J106: Amazon Fulfillment Center(LBA2) | K106: 0000 000 0000 | L106: UK
A107: UK | B107: FBA仓 | C107: MAN2 | D107: 英国 | E107: Omega Plot 7c Orion Boulevard | G107: Warrington North West England | H107: WA5 3XA | I107: Amazon(MAN2) | J107: Amazon Fulfillment Center(MAN2) | K107: 0000 000 0000 | L107: UK
A108: JP | B108: FBA仓 | C108: NRT5 | D108: 日本 | E108: 埼玉県川越市南台1-10-15 | F108: 埼玉県 | G108: 埼玉 | H108: 350-1182 | I108: amazon.com | J108: Amazon NRT5 | K108: 0000000000 | L108: JP
A109: JP | B109: FBA仓 | C109: HND3 | D109: 日本 | E109: 埼玉県比企郡川島町かわじま2-1-1 2F | F109: 埼玉県 | G109: 比企郡 | H109: 350-0195 | I109: amazon.com | J109: Amazon HND3 | K109: 0000000000 | L109: JP
A110: JP | B110: FBA仓 | C110: KIX1 | D110: 日本 | E110: 大阪府堺市堺区築港八幡町138-7 | F110: 大阪府 | G110: 堺市 | H110: 590-8589 | I110: amazon.com | J110: Amazon KIX1 | K110: 0000000000 | L110: JP
A111: JP | B111: FBA仓 | C111: KIX2 | D111: 日本 | E111: 大阪府大東市緑が丘2-1-1 | F111: 大阪府 | G111: 大東市 | H111: 574-8531 | I111: amazon.com | J111: Amazon KIX2 | K111: 0000000000 | L111: JP
A112: JP | B112: FBA仓 | C112: HSG1 | D112: 日本 | E112: 佐賀県鳥栖市弥生が丘3-1-3 | F112: 佐賀県 | G112: 鳥栖市 | H112: 841-8505 | I112: amazon.com | J112: Amazon HSG1 | K112: 0000000000 | L112: JP
A113: JP | B113: FBA仓 | C113: FSZ1 | D113: 日本 | E113: 神奈川県小田原市扇町4-5-1 | F113: 神奈川県 | G113: 小田原市 | H113: 250-8560 | I113: amazon.com | J113: Amazon FSZ1 | K113: 0000000000 | L113: JP
A114: JP | B114: FBA仓 | C114: NRT1 | D114: 日本 | E114: 千葉県市川市塩浜2-13-1 | F114: 千葉県 | G114: 市川市 | H114: 272-0193 | I114: amazon.com | J114: Amazon NRT1 | K114: 0000000000 | L114: JP
A115: JP | B115: FBA仓 | C115: NRT2 | D115: 日本 | E115: 千葉県八千代市上高野2036 | F115: 千葉県 | G115: 八千代市 | H115: 276-8525 | I115: amazon.com | J115: Amazon NRT2 | K115: 0000000000 | L115: JP
A116: JP | B116: FBA仓 | C116: KIX4 | D116: 日本 | E116: 大阪府藤井寺市津堂4-435 | F116: 大阪府 | G116: 藤井寺市 | H116: 583-8533 | I116: amazon.com | J116: Amazon KIX4 | K116: 0000000000 | L116: JP
A117: ES | B117: FBA仓 | C117: BCN1 | D117: 西班牙 | E117: Av. de les Garrigues num. 6-8 El Prat de Llobregat El Prat de Llobregat | F117: Barcelona | H117: 08820 | I117: Amazon (BCN1) | J117: Amazon Fulfillment Center BCN1 | K117: 0000000000 | L117: ES
A118: IT | B118: FBA仓 | C118: MXP5 | D118: 意大利 | E118: Strada Dogana Po, 2U | F118: Province of Piacenza | G118: Castel San Giovanni | H118: 29015 | I118: Amazon (MXP5) | J118: Amazon Fulfillment Center MXP5 | K118: 0000000000 | L118: IT
A119: IT | B119: FBA仓 | C119: FCO1 | D119: 意大利 | E119: Via della Meccanica snc | F119: Rieti | G119: Passo Corese RI | H119: 02032 | I119: Amazon (FCO1) | J119: Amazon Fulfillment Center FCO1 | K119: 0000000000 | L119: IT
A120: FR | B120: FBA仓 | C120: ORY1 | D120: 法国 | E120: Pole 45 1401 rue du Champ Rouge SARAN CEDEX | G120: Saran | H120: 45772 | I120: Amazon (ORY1) | J120: Amazon Fulfillment Center ORY1 | K120: 0000000000 | L120: FR
A121: FR | B121: FBA仓 | C121: MRS1 | D121: 法国 | E121: ZAC les Portes de Provence,CEDEX | G121: Montelimar | H121: 26132 | I121: Amazon (MRS1) | J121: Amazon Fulfillment Center MRS1 | K121: 0000000000 | L121: FR
A122: FR | B122: FBA仓 | C122: LYS1 | D122: 法国 | E122: Distripôle Châlons ZAC Val de Bourgogne,CEDEX | G122: Severy | H122: 71311 | I122: Amazon (LYS1) | J122: Amazon Fulfillment Center LYS1 | K122: 0000000000 | L122: FR
A123: FR | B123: FBA仓 | C123: LIL1 | D123: 法国 | E123: 1, Rue Amazon Lauwin Planque | G123: CEDEX | H123: 59353 | I123: Amazon(LIL1) | J123: Amazon Fulfillment Center LIL1 | K123: 0000000000 | L123: FR
A124: FR | B124: FBA仓 | C124: XFRG | D124: 法国 | E124: XPO Artenay NS 3PL ZAC du Moulin Artenay | G124: Moulin | H124: 45410 | I124: Amazon(XFRG) | J124: Amazon Fulfillment Center XFRG | K124: 0000000000 | L124: FR
A125: US | B125: FBA仓 | C125: MDT2 | D125: 美国 | E125: 600 Principio Parkway West | F125: MD | G125: North East | H125: 21901 | I125: Amazon Fulfillment Center MDT2 | J125: Amazon Fulfillment Center MDT2 | K125: 0000000000 | L125: US
A126: UK | B126: FBA仓 | C126: LCY2 | D126: 英国 | E126: Depot Unit 2, London Distribution Park | G126: Tilbury | H126: RM18 7AN | I126: Amazon(LCY2) | J126: Amazon Fulfillment Center(LCY2) | K126: 0000 000 0000 | L126: UK
A127: FR | B127: FBA仓 | C127: BVA1 | D127: 法国 | E127: Avenue du Superbe Orenoque AMIENS CEDEX Hauts-de-France | G127: AMIENS | H127: 80337 | I127: Amazon(BVA1) | J127: Amazon Fulfillment Center BVA1 | K127: 0000000000 | L127: FR
A128: IT | B128: FBA仓 | C128: MXP3 | D128: 意大利 | E128: Via Rita Levi Montalcini, 2 Vercelli | G128: Piedmont | H128: 13100 | I128: Amazon (MXP3) | J128: Amazon Fulfillment Center MXP3 | K128: 0000000000 | L128: IT
A129: US | B129: FBA仓 | C129: ONT5 | D129: 美国 | E129: 2020 E. Central Ave. Southgate Building 4 | F129: CA | G129: San Bernardino | H129: 92408-2606 | I129: Amazon Fulfillment Center ONT5 | J129: Amazon Fulfillment Center ONT5 | K129: 0000000000 | L129: US
A130: US | B130: FBA仓 | C130: SNA6 | D130: 美国 | E130: 5250 Goodman Road | F130: CA | G130: Eastvale | H130: 91752 | I130: Amazon Fulfillment Center SNA6 | J130: Amazon Fulfillment Center SNA6 | K130: 0000000000 | L130: US
A131: US | B131: FBA仓 | C131: LAS6 | D131: 美国 | E131: 4550 Nexus WayLas Vegas, NV 89115-1826 | F131: NV | G131: LasVegas | H131: 89115 | I131: Amazon Fulfillment Center LAS6 | J131: Amazon Fulfillment Center LAS6 | K131: 0000000000 | L131: US
A132: US | B132: FBA仓 | C132: DEN2 | D132: 美国 | E132: 22205 east 19th ave aurora CO 80019 | F132: CO | G132: Aurora | H132: 80019 | I132: Amazon Fulfillment Center DEN2 | J132: Amazon Fulfillment Center DEN2 | K132: 0000000000 | L132: US
A133: US | B133: FBA仓 | C133: MCI5 | D133: 美国 | E133: 16851 W 113th St | F133: KS | G133: Lenexa | H133: 66219 | I133: Amazon Fulfillment Center MCI5 | J133: Amazon Fulfillment Center MCI5 | K133: 0000000000 | L133: US
A134: US | B134: FBA仓 | C134: MKE5 | D134: 美国 | E134: 11211 Burlington Road | F134: WI | G134: Kenosha | H134: 53144 | I134: Amazon Fulfillment Center MKE5 | J134: Amazon Fulfillment Center MKE5 | K134: 0000000000 | L134: US
A135: US | B135: FBA仓 | C135: CMH1 | D135: 美国 | E135: 11999 National Road SW Etna | F135: OH | G135: SW Etna | H135: 43062-7793 | I135: Amazon Fulfillment Center CMH1 | J135: Amazon Fulfillment Center CMH1 | K135: 0000000000 | L135: US
A136: US | B136: FBA仓 | C136: ABE4 | D136: 美国 | E136: 1610 Van Buren Road Easton, PA 18045-7807 | F136: PA | G136: Easton | H136: 18045-7807 | I136: Amazon Fulfillment Center ABE4 | J136: Amazon Fulfillment Center ABE4 | K136: 0000000000 | L136: US
A137: UK | B137: FBA仓 | C137: BHX4 | D137: 英国 | E137: Plot 1, Lyons Park, Sayer Dr | F137: West Midlands | G137: Coventry | H137: CV5 9PF | I137: Amazon(BHX4) | J137: Amazon Fulfillment Center(BHX4) | K137: 0000 000 0000 | L137: UK
A138: UK | B138: FBA仓 | C138: MAN3 | D138: 英国 | E138: 360 Logistics North, Over Hulton | F138: North West | G138: BOLTON | H138: BL5 1EE | I138: Amazon(MAN3) | J138: Amazon Fulfillment Center(MAN3) | K138: 0000 000 0000 | L138: UK
A139: JP | B139: FBA仓 | C139: TPF3 | D139: 日本 | E139: Lawn Town 1-52-2,Takatsuki City, Osaka prefecture 569-0823,JP (TPF 3) | G139: Takatsuki City | H139: 569-0823 | I139: TPF3 | J139: Amazon TPF3 | K139: 0000000000 | L139: JP
A140: US | B140: FBA仓 | C140: HOU3 | D140: 美国 | E140: 31555 Highway 90 E Brookshire TX 77423-2769 | F140: TX | G140: Brookshire | H140: 77423-2769 | I140: Amazon Fulfillment Center HOU3 | J140: Amazon Fulfillment Center HOU3 | K140: 0000000000 | L140: US
A141: US | B141: FBA仓 | C141: IVSF | D141: 美国 | E141: 2821 MARION DR STE 109 | F141: NV | G141: LAS VEGAS | H141: 89115-3477 | I141: Amazon Fulfillment Center IVSF | J141: Amazon Fulfillment Center IVSF | K141: 0000000000 | L141: US
A142: US | B142: FBA仓 | C142: BWI4 | D142: 美国 | E142: 165 Business Blvd Clear Brook, VA 22624-1568 US BWI4 | F142: VA | G142: Clear Brook | H142: 22624-1568 | I142: Amazon Fulfillment Center BWI4 | J142: Amazon Fulfillment Center BWI4 | K142: 0000000000 | L142: US
A143: US | B143: FBA仓 | C143: SMF3 | D143: 美国 | E143: 3923 S B ST | F143: CA | G143: Stockton | H143: 95206-8202 | I143: Amazon Fulfillment Center SMF3 | J143: Amazon Fulfillment Center SMF3 | K143: 0000000000 | L143: US
A144: DE | B144: FBA仓 | C144: EDEA | D144: 德国 | E144: Warmbreitbandstr. 3 | G144: Dortmund | H144: 44145 | I144: Amazon (EDEA) | J144: Amazon Fulfillment Center EDEA | K144: 0000000000 | L144: DE
A145: US | B145: FBA仓 | C145: IVSE | D145: 美国 | E145: 2951 MARION DR UNIT 101 LAS VEGAS, NV 89115-3467 | F145: NV | G145: LAS VEGAS | H145: 89115-3467 | I145: Amazon Fulfillment Center IVSE | J145: Amazon Fulfillment Center IVSE | K145: 0000000000 | L145: US
A146: US | B146: FBA仓 | C146: ITX2 | D146: 美国 | E146: 6911 FAIRBANKS N HOUSTON RD SUITE 160 Houston, TX 77040-1437 | F146: TX | G146: Houston | H146: 77040-1437 | I146: Amazon Fulfillment Center ITX2 | J146: Amazon Fulfillment Center ITX2 | K146: 0000000000 | L146: US
A147: US | B147: FBA仓 | C147: MEM1 | D147: 美国 | E147: 3292 E Holmes Rd Memphis,TN 38118-8102 US | F147: TN | G147: Memphis | H147: 38118 | I147: Amazon Fulfillment Center MEM1 | J147: Amazon Fulfillment Center MEM1 | K147: 0000000000 | L147: US
A148: US | B148: FBA仓 | C148: CLT3 | D148: 美国 | E148: 6500 Davidson Hwy Concord, NC 28027-7995 US | F148: NC | G148: Concord | H148: 28027-7995 | I148: Amazon Fulfillment Center CLT3 | J148: Amazon Fulfillment Center CLT3 | K148: 0000000000 | L148: US
A149: JP | B149: FBA仓 | C149: KIX3 | D149: 日本 | E149: 松下町2-1 茨木市, 大阪府 567-8507 | G149: 茨木市 | H149: 5678507 | I149: Amazon.co.jp | J149: Amazon KIX3 | K149: 0000000000 | L149: JP
A150: JP | B150: FBA仓 | C150: HND9 | D150: 日本 | E150: 高津区北見方3-14-1 川崎市, 神奈川県 213-8517 JP (HND9) | G150: 川崎市 | H150: 2138517 | I150: Amazon.co.jp | J150: Amazon HND9 | K150: 0000000000 | L150: JP
A151: JP | B151: FBA仓 | C151: TPF6 | D151: 日本 | E151: 松崎台2-4-1印西市, 千葉県 270-1389 | G151: 印西市 | H151: 270-1389 | I151: Amazon.co.jp | J151: Amazon TPF6 | K151: 0000000000 | L151: JP
A152: ES | B152: FBA仓 | C152: MAD6 | D152: 西班牙 | E152: Avenida de la Logistica poligono industrial veredilla III illescas Toledo, Castile-La | F152: Mancha | G152: Toledo | H152: 45200 | I152: Amazon (MAD6) | J152: Amazon Fulfillment Center MAD6 | K152: 0000000000 | L152: ES
A153: US | B153: FBA仓 | C153: DET2 | D153: 美国 | E153: 50500 Mound Rd Shelby Township, MI 48317-1318 | F153: MI | G153: Township | H153: 48317 | I153: Amazon Fulfillment Center DET2 | J153: Amazon Fulfillment Center DET2 | K153: 0000000000 | L153: US
A154: UK | B154: FBA仓 | C154: BHX3 | D154: 英国 | E154: 4 Royal Oak Way North Daventry, Northamptonshire | F154: Northamptonshire | G154: Daventry | H154: NN11 8QL | I154: Amazon(BHX3) | J154: Amazon Fulfillment Center(BHX3) | K154: 0000 000 0000 | L154: UK
A155: US | B155: FBA仓 | C155: LAX9 | D155: 美国 | E155: 11263 Oleander Ave FONTANA CA | F155: CA | G155: FONTANA | H155: 92337 | I155: Amazon Fulfillment Center LAX9 | J155: Amazon Fulfillment Center LAX9 | K155: 0000000000 | L155: US
A156: UK | B156: FBA仓 | C156: BRS1 | D156: 英国 | E156: Goldcrest Way Bristol, South West | G156: Bristol | H156: BS35 4DJ | I156: Amazon(BRS1) | J156: Amazon Fulfillment Center(BRS1) | K156: 0000 000 0000 | L156: UK
A157: US | B157: FBA仓 | C157: CMH3 | D157: 美国 | E157: 700 GATEWAY BLVD Monroe, OH 45050-1848 | F157: OH | G157: Monroe | H157: 45050 | I157: Amazon Fulfillment Center CMH3 | J157: Amazon Fulfillment Center CMH3 | K157: 0000000000 | L157: US
A158: IT | B158: FBA仓 | C158: TRN1 | D158: 意大利 | E158: Strada Provinciale per Rondissone 90,Torrazza | G158: Piemonte | H158: 10037 | I158: Amazon (TRN1) | J158: Amazon Fulfillment Center TRN1 | K158: 0000000000 | L158: IT
A159: UK | B159: FBA仓 | C159: EMA1 | D159: 英国 | E159: Unit 1, Wilders Way | F159: England | G159: Derby | H159: DE74 2BB | I159: Amazon(EMA1) | J159: Amazon Fulfillment Center(EMA1) | K159: 0000 000 0000 | L159: UK
A160: FR | B160: FBA仓 | C160: ORY4 | D160: 法国 | E160: Avenue du Centre d’Essais en Vol | G160: Brétigny sur Orge | H160: 91225 | I160: Amazon (ORY4) | J160: Amazon Fulfillment Center ORY4 | K160: 0000000000 | L160: FR
A161: US | B161: FBA仓 | C161: SAV3 | D161: 美国 | E161: 7001 Skipper Rd Macon, GA 31216-6427 | F161: GA | G161: Macon | H161: 31216 | I161: Amazon Fulfillment Center SAV3 | J161: Amazon Fulfillment Center SAV3 | K161: 0000000000 | L161: US
A162: US | B162: FBA仓 | C162: IND9 | D162: 美国 | E162: 1151 S GRAHAM RD GREENWOOD, IN 46143-7830 | F162: IN | G162: GREENWOOD | H162: 46143 | I162: Amazon Fulfillment Center IND9 | J162: Amazon Fulfillment Center IND9 | K162: 0000000000 | L162: US
A163: US | B163: FBA仓 | C163: VINE | D163: 美国 | E163: 500 Duke Dr Lebanon, TN 37090-8123 | F163: TN | G163: Lebanon | H163: 37090 | I163: Amazon Fulfillment Center VINE | J163: Amazon Fulfillment Center VINE | K163: 0000000000 | L163: US
A164: UK | B164: FBA仓 | C164: MAN4 | D164: 英国 | E164: 29 Gander Lane | F164: England | G164: CHESTERFIELD | H164: S43 4PZ | I164: Amazon(MAN4) | J164: Amazon Fulfillment Center(MAN4) | K164: 0000 000 0000 | L164: UK
A165: US | B165: FBA仓 | C165: IVSC | D165: 美国 | E165: 1225 Forest Parkway West Deptford, NJ 08066-1743 | F165: NJ | G165: West Deptford | H165: 08066 | I165: Amazon Fulfillment Center IVSC | J165: Amazon Fulfillment Center IVSC | K165: 0000000000 | L165: US
A166: US | B166: FBA仓 | C166: PDX7 | D166: 美国 | E166: 4775 Depot Ct SE Salem, OR 97317-8983 | F166: OR | G166: Salem | H166: 97317 | I166: Amazon Fulfillment Center PDX7 | J166: Amazon Fulfillment Center PDX7 | K166: 0000000000 | L166: US
A167: UK | B167: FBA仓 | C167: XBH1 | D167: 英国 | E167: XPO Logistics, Unit A Daventry Distribution Centre, Royal Oak Way North.Daventry, Leicestershir | G167: Daventry | H167: NN11 8LR | I167: Amazon(XBH1) | J167: Amazon Fulfillment Center(XBH1) | K167: 0000 000 0000 | L167: UK
A168: US | B168: FBA仓 | C168: ACY2 | D168: 美国 | E168: 1101 E PEARL ST | F168: NJ | G168: BURLINGTON | H168: 08016-1934 | I168: Amazon Fulfillment Center ACY2 | J168: Amazon Fulfillment Center ACY2 | K168: 0000000000 | L168: US
A169: IT | B169: FBA仓 | C169: XMP2 | D169: 意大利 | E169: Via Aldo Moro 4 | F169: Carpiano | G169: Francolino di | H169: 20080 | I169: Amazon (XMP2) | J169: Amazon Fulfillment Center XMP2 | K169: 0000000000 | L169: IT
A170: JP | B170: FBA仓 | C170: KIX5 | D170: 日本 | E170: "松井宮田1 京田辺市, 京都府 610-0397 | F170: 京都府 | G170: 京田辺市 | H170: 610-0397 | I170: Amazon.co | J170: Amazon KIX5 | K170: 0000000000 | L170: JP
A171: US | B171: FBA仓 | C171: FTW3 | D171: 美国 | E171: 15201 Heritage Pkwy Fort Worth, TX 76177-2517 | F171: TX | G171: Fort Worth | H171: 76177 | I171: Amazon Fulfillment Center FTW3 | J171: Amazon Fulfillment Center FTW3 | K171: 0000000000 | L171: US
A172: UK | B172: FBA仓 | C172: MME1 | D172: 英国 | E172: Building One Symmetry Park | F172: England | G172: Darlington | H172: DL1 4BF | I172: Amazon(MME1) | J172: Amazon Fulfillment Center(MME1) | K172: 0000 000 0000 | L172: UK
A173: IT | B173: FBA仓 | C173: XMP1 | D173: 意大利 | E173: Via Maestri Del Lavoro,990 | F173: Rovigo | G173: Arqua Polesine | H173: 45031 | I173: Amazon (XMP1) | J173: Amazon Fulfillment Center XMP1 | K173: 0000000000 | L173: IT
...

Sheet 指定路线
A1: 路线编码 | B1: 路线名称 | C1: 清关方式
A2: S-UK22S | B2: 英国海运-快递派(ZS)-华南 | C2: 自税
A3: T-UK21S | B3: 英国卡航-快递派(ZS)-华南 | C3: 自税
A4: S-UK23S | B4: 英国海运-卡派(ZS)-CBM-华南 | C4: 自税
A5: A-EU002 空-欧洲特惠（HS） | B5: 空-欧洲特惠（HS） | C5: 包税
A6: A-EU002-B 空-欧洲特惠（HS）-带电 | B6: 空-欧洲特惠（HS）-带电 | C6: 包税
A7: A-EU003 空-德国专线（HS） | B7: 空-德国专线（HS） | C7: 自税
A8: A-EU003-B 空-德国专线（HS）-带电 | B8: 空-德国专线（HS）-带电 | C8: 自税
A9: A-EU004 空-欧洲特惠（ZS） | B9: 空-欧洲特惠（ZS） | C9: 自税
A10: A-EU004-B 空-欧洲特惠（ZS）-带电 | B10: 空-欧洲特惠（ZS）-带电 | C10: 自税
A11: A-UK002 空-英国特惠（ZS） | B11: 空-英国特惠（ZS） | C11: 自税
A12: A-UK002-A 空-英国特惠（HS) | B12: 空-英国特惠（HS) | C12: 包税
... A192: T-EU23S | B192: 欧洲卡航-嘀卡陆航卡派递延(ZS)-华南 | C192: 自税
